ttdet/__init__.py
ttdet/base_detectron.py
ttdet/classifier.py
ttdet/deeptext_recognizer.py
ttdet/detectron2_predictor.py
ttdet/fasterrcnn_detectron.py
ttdet/fasterrcnn_tester.py
ttdet/maskrcnn_detectron.py
ttdet/maskrcnn_tester.py
ttdet/model.py
ttdet/moran_text_recognizer.py
ttdet/object_detector.py
ttdet/siamese_tester.py
ttdet/template_matching.py
ttdet/R3det_rotObj_detect/__init__.py
ttdet/R3det_rotObj_detect/r3det.py
ttdet/R3det_rotObj_detect/dataio/__init__.py
ttdet/R3det_rotObj_detect/dataio/convert_data_to_tfrecord.py
ttdet/R3det_rotObj_detect/dataio/image_preprocess.py
ttdet/R3det_rotObj_detect/dataio/image_preprocess_multi_gpu.py
ttdet/R3det_rotObj_detect/dataio/read_tfrecord.py
ttdet/R3det_rotObj_detect/dataio/read_tfrecord_multi_gpu.py
ttdet/R3det_rotObj_detect/help_utils/__init__.py
ttdet/R3det_rotObj_detect/help_utils/tools.py
ttdet/R3det_rotObj_detect/libs/__init__.py
ttdet/R3det_rotObj_detect/libs/setup.py
ttdet/R3det_rotObj_detect/libs/box_utils/__init__.py
ttdet/R3det_rotObj_detect/libs/box_utils/anchor_utils.py
ttdet/R3det_rotObj_detect/libs/box_utils/bbox_transform.py
ttdet/R3det_rotObj_detect/libs/box_utils/boxes_utils.py
ttdet/R3det_rotObj_detect/libs/box_utils/coordinate_convert.py
ttdet/R3det_rotObj_detect/libs/box_utils/draw_box_in_img.py
ttdet/R3det_rotObj_detect/libs/box_utils/generate_anchors.py
ttdet/R3det_rotObj_detect/libs/box_utils/generate_rotate_anchors.py
ttdet/R3det_rotObj_detect/libs/box_utils/iou.py
ttdet/R3det_rotObj_detect/libs/box_utils/iou_rotate.py
ttdet/R3det_rotObj_detect/libs/box_utils/mask_utils.py
ttdet/R3det_rotObj_detect/libs/box_utils/nms_rotate.py
ttdet/R3det_rotObj_detect/libs/box_utils/setup.py
ttdet/R3det_rotObj_detect/libs/box_utils/show_box_in_tensor.py
ttdet/R3det_rotObj_detect/libs/box_utils/tf_ops.py
ttdet/R3det_rotObj_detect/libs/box_utils/cython_utils/__init__.py
ttdet/R3det_rotObj_detect/libs/box_utils/cython_utils/setup.py
ttdet/R3det_rotObj_detect/libs/configs__aa/__init__.py
ttdet-1.0.9.dist-info/LICENSE
ttdet-1.0.9.dist-info/METADATA
ttdet-1.0.9.dist-info/WHEEL
ttdet-1.0.9.dist-info/top_level.txt
ttdet-1.0.9.dist-info/RECORD
