Metadata-Version: 2.1
Name: ttdet
Version: 1.0.9
Summary: A vision utilities for computer vision
Home-page: https://github.com/mtbui2010
Author: Trung M. Bui
Author-email: bmtrungvp@gmail.com
License: MIT
Keywords: AI,DETECTION,UTILITY
Platform: UNKNOWN
Classifier: Programming Language :: Python :: 3
Classifier: License :: OSI Approved :: MIT License
Classifier: Operating System :: OS Independent
Requires-Python: >=3.6
Requires-Dist: numpy
Requires-Dist: opencv-python
Requires-Dist: scipy
Requires-Dist: matplotlib
